[{"brand":"Adidas","category":"Sport shoes","items":[]},{"brand":"Nike","category":"Sport shoes","items":[]},{"brand":"Hotter","category":"Women's shoes","items":[]},{"brand":"Irregular Choice","category":"Women's shoes","items":[]},{"brand":"Skechers","category":"Women's shoes","items":[]},{"brand":"Skechers","category":"Men's shoes","items":[]},{"brand":"Skechers","category":"Girls' Shoes","items":[]},{"brand":"Skechers","category":"Boys' Shoes","items":[]},{"brand":"Skechers","category":"Baby shoes","items":[{"asin":"B09DRMTY3F","imageUrl":"https://m.media-amazon.com/images/I/61A8D9177CL._AC_UL400_.jpg","price":15.9,"name":"Skechers"},{"asin":"B06XFJPTTL","imageUrl":"https://m.media-amazon.com/images/I/61LPzToq2SL._AC_UL400_.jpg","price":29.52,"name":"Skechers"}]},{"brand":"Rieker","category":"Women's shoes","items":[]},{"brand":"Rieker","category":"Men's shoes","items":[{"asin":"B08WX9MJY8","imageUrl":"https://m.media-amazon.com/images/I/71rFp5lfF-L._AC_UL320_.jpg","price":23.8,"name":"Rieker Mens Casual Lace Up Tex Boots F9620"}]},{"brand":"Clarks","category":"Women's shoes","items":[]},{"brand":"Clarks","category":"Men's shoes","items":[]},{"brand":"Clarks","category":"Baby shoes","items":[]},{"brand":"Geox","category":"Women's shoes","items":[]},{"brand":"Geox","category":"Men's shoes","items":[{"asin":"B06XNYQ42C","imageUrl":"https://m.media-amazon.com/images/I/71UbUwCv4nL._AC_UL400_.jpg","price":16.78,"name":"Geox Men's U Happy Art. H Sneakers"},{"asin":"B0825NZVZ7","imageUrl":"https://m.media-amazon.com/images/I/61QDnr49rKL._AC_UL400_.jpg","price":19.48,"name":"Geox Men's U Timothy a Oxford Flat"},{"asin":"B0825P4V7J","imageUrl":"https://m.media-amazon.com/images/I/61zOuT1E2YL._AC_UL400_.jpg","price":19.6,"name":"Geox Men's U Timothy C Shoes"},{"asin":"B09KNGQVFY","imageUrl":"https://m.media-amazon.com/images/I/71M5AMqzqkL._AC_UL400_.jpg","price":20.17,"name":"Geox Herren U Terrestre B WPF A Sneakers"},{"asin":"B07SVPPFMD","imageUrl":"https://m.media-amazon.com/images/I/71qIpc3RbPL._AC_UL400_.jpg","price":21.37,"name":"Geox Men's U Snake.2 a Sneaker"},{"asin":"B0B298TWHS","imageUrl":"https://m.media-amazon.com/images/I/51YOWrLI9iL._AC_UL400_.jpg","price":21.51,"name":"Geox Men's J Ghita Boy Sandal"},{"asin":"B0B29GXTBP","imageUrl":"https://m.media-amazon.com/images/I/81-leXI-sfL._AC_UL400_.jpg","price":22.28,"name":"Geox Boy's J Aril Sneaker"},{"asin":"B0825P35F1","imageUrl":"https://m.media-amazon.com/images/I/71o2SwX7DlL._AC_UL400_.jpg","price":22.39,"name":"Geox Men's U Levico B ABX B Sneaker"},{"asin":"B0B298JTJ8","imageUrl":"https://m.media-amazon.com/images/I/71zrgbWp7LL._AC_UL400_.jpg","price":23.22,"name":"Geox Men's J Ghita Boy Sandal"},{"asin":"B0B299W32L","imageUrl":"https://m.media-amazon.com/images/I/61hJKOfzfmL._AC_UL400_.jpg","price":23.62,"name":"Geox Boy's J Sandal Splush"},{"asin":"B0B294WMQP","imageUrl":"https://m.media-amazon.com/images/I/81c0EcsbGhL._AC_UL400_.jpg","price":23.94,"name":"Geox Men's U Portello Sneaker"},{"asin":"B0B299CCD3","imageUrl":"https://m.media-amazon.com/images/I/71twVs6M99L._AC_UL400_.jpg","price":24.04,"name":"Geox Men's J Pavel Sneaker, White Silver, 12.5 UK Narrow"},{"asin":"B09N7L2CBS","imageUrl":"https://m.media-amazon.com/images/I/71W61sY4ZML._AC_UL400_.jpg","price":24.16,"name":"Geox Man U Pg1X Abx A Sneakers"},{"asin":"B07SSJW5NW","imageUrl":"https://m.media-amazon.com/images/I/71dR475ZCIL._AC_UL400_.jpg","price":28.34,"name":"Geox Men's U Bayle B Chelsea Boots"}]},{"brand":"Geox","category":"Baby shoes","items":[]}]
